Metadata-Version: 2.4
Name: mcp-paradex
Version: 0.1.1
Summary: MCP server for Paradex trading platform integration
Author-email: Your Name <your.email@example.com>
License-Expression: MIT
License-File: LICENSE
Classifier: Development Status :: 3 - Alpha
Classifier: Intended Audience :: Developers
Classifier: License :: OSI Approved :: MIT License
Classifier: Programming Language :: Python :: 3
Classifier: Programming Language :: Python :: 3.10
Classifier: Programming Language :: Python :: 3.11
Classifier: Programming Language :: Python :: 3.12
Requires-Python: >=3.10
Requires-Dist: aiohttp>=3.12.0
Requires-Dist: argparse>=1.4.0
Requires-Dist: jmespath>=1.0.1
Requires-Dist: mcp[cli]>=1.10.1
Requires-Dist: paradex-py>=0.4.6
Requires-Dist: pydantic>=2.11.0
Requires-Dist: python-dotenv>=1.0.1
Requires-Dist: uvicorn>=0.35.0
Provides-Extra: dev
Requires-Dist: black>=25.1.0; extra == 'dev'
Requires-Dist: mypy>=1.15.0; extra == 'dev'
Requires-Dist: pre-commit>=4.2.0; extra == 'dev'
Requires-Dist: pytest-cov>=6.0.0; extra == 'dev'
Requires-Dist: pytest>=8.3.5; extra == 'dev'
Requires-Dist: ruff>=0.11.2; extra == 'dev'
